celltk/__init__.py
celltk/evaluate.py
celltk/extract.py
celltk/process.py
celltk/segment.py
celltk/track.py
celltk/core/arrays.py
celltk/core/operation.py
celltk/core/orchestrator.py
celltk/core/pipeline.py
celltk/external/kit_sch_ge/__init__.py
celltk/external/kit_sch_ge/config.py
celltk/external/kit_sch_ge/create_synth_segm_data.py
celltk/external/kit_sch_ge/run_tracking.py
celltk/external/kit_sch_ge/setup.py
celltk/external/kit_sch_ge/tracker/__init__.py
celltk/external/kit_sch_ge/tracker/export.py
celltk/external/kit_sch_ge/tracker/extract_data.py
celltk/external/kit_sch_ge/tracker/flow.py
celltk/external/kit_sch_ge/tracker/graph.py
celltk/external/kit_sch_ge/tracker/postprocessing.py
celltk/external/kit_sch_ge/tracker/split_objects.py
celltk/external/kit_sch_ge/tracker/tracking.py
celltk/external/kit_sch_ge/tracker/utils.py
celltk/external/misic/MiSiCv2.h5
celltk/external/misic/__init__.py
celltk/external/misic/extras.py
celltk/external/misic/misic.py
celltk/external/misic/utils.py
celltk/utils/__init__.py
celltk/utils/_fastkde.py
celltk/utils/_types.py
celltk/utils/bayes_utils.py
celltk/utils/cli_utils.py
celltk/utils/estimator_utils.py
celltk/utils/file_utils.py
celltk/utils/filter_utils.py
celltk/utils/kit_sch_ge_utils.py
celltk/utils/log_utils.py
celltk/utils/metric_utils.py
celltk/utils/operation_utils.py
celltk/utils/peak_utils.py
celltk/utils/plot_utils.py
celltk/utils/process_utils.py
celltk/utils/slurm_utils.py
celltk/utils/unet_model.py
celltk/utils/utils.py
celltk2-0.4.3.dist-info/LICENSE
celltk2-0.4.3.dist-info/METADATA
celltk2-0.4.3.dist-info/WHEEL
celltk2-0.4.3.dist-info/top_level.txt
celltk2-0.4.3.dist-info/RECORD
