Metadata-Version: 2.1
Name: celltk2
Version: 0.4.3
Summary: A toolkit for analysis of live-cell microscopy images
Home-page: https://github.com/sjeknic/CellTK
Author: Stevan Jeknic
Author-email: sjeknic <sjeknic@stanford.edu>
Project-URL: Homepage, https://github.com/sjeknic/CellTK/
Project-URL: Bug Tracker, https://github.com/sjeknic/CellTK/issues
Project-URL: Documentation, https://celltk.readthedocs.io/en/latest/
Classifier: Programming Language :: Python :: 3
Classifier: License :: OSI Approved :: MIT License
Classifier: Operating System :: OS Independent
Requires-Python: >=3.9
License-File: LICENSE
Requires-Dist: setuptools (>=41.2.0)
Requires-Dist: numpy (<1.23,>=1.20)
Requires-Dist: scipy (>=1.6.3)
Requires-Dist: scikit-learn (>=1.0.1)
Requires-Dist: scikit-image (>=0.19.1)
Requires-Dist: matplotlib (>=3.4.1)
Requires-Dist: plotly (>=5.6.0)
Requires-Dist: pandas (>=1.3.1)
Requires-Dist: h5py (>=3.6.0)
Requires-Dist: imageio (>=2.13.0)
Requires-Dist: mahotas (<1.4.13,>=1.4.5)
Requires-Dist: PyYAML (>=6.0)
Requires-Dist: SimpleITK (>=2.1.1)
Requires-Dist: tifffile (>=2021.11.2)
Requires-Dist: colorcet (~=3.0.0)
Requires-Dist: seaborn (~=0.11.2)
Requires-Dist: tensorflow (<2.10.0,>=2.7.0) ; platform_machine != "arm64"
Requires-Dist: tensorflow-macos (<2.10.0,>=2.7.0) ; platform_machine == "arm64"
Provides-Extra: btrack
Requires-Dist: btrack (==0.4.2) ; extra == 'btrack'
Provides-Extra: kit
Requires-Dist: gurobipy (>=9.5.0) ; extra == 'kit'
Requires-Dist: kvxopt (~=1.3.0.2) ; extra == 'kit'
Provides-Extra: test
Requires-Dist: pytest (>=7.0) ; extra == 'test'
Requires-Dist: ipdb (>=0.13) ; extra == 'test'
